{"title": "Paska-Ankka 2: Electric Boogaloo", "id": "tg-2209456005991890946", "net.maunium.telegram.pack": {"short_name": "PaskaAnkkaRedux", "hash": "56910967"}, "stickers": [{"body": "😠", "url": "mxc://matrix.org/BkqUxHGQUzdGifzaHgsjkUMs", "info": {"w": 256, "h": 168, "size": 228100, "mimetype": "image/png", "thumbnail_url": "mxc://matrix.org/BkqUxHGQUzdGifzaHgsjkUMs", "thumbnail_info": {"w": 256, "h": 168, "size": 228100, "mimetype": "image/png"}}, "msgtype": "m.sticker", "id": "tg-2209456005991890962", "net.maunium.telegram.sticker": {"pack": {"id": "2209456005991890946", "short_name": "PaskaAnkkaRedux"}, "id": "2209456005991890962", "emoticons": ["😠"]}}, {"body": "🥃", "url": "mxc://matrix.org/fdYFiYwoIWhBXKPxjHHgrkkZ", "info": {"w": 210, "h": 256, "size": 287357, "mimetype": "image/png", "thumbnail_url": "mxc://matrix.org/fdYFiYwoIWhBXKPxjHHgrkkZ", "thumbnail_info": {"w": 210, "h": 256, "size": 287357, "mimetype": "image/png"}}, "msgtype": "m.sticker", "id": "tg-2209456005991890963", "net.maunium.telegram.sticker": {"pack": {"id": "2209456005991890946", "short_name": "PaskaAnkkaRedux"}, "id": "2209456005991890963", "emoticons": ["🥃"]}}, {"body": "😵", "url": "mxc://matrix.org/uWcQsFwfwTRxpklhJNSzgtZH", "info": {"w": 256, "h": 152, "size": 252694, "mimetype": "image/png", "thumbnail_url": "mxc://matrix.org/uWcQsFwfwTRxpklhJNSzgtZH", "thumbnail_info": {"w": 256, "h": 152, "size": 252694, "mimetype": "image/png"}}, "msgtype": "m.sticker", "id": "tg-2209456005991890964", "net.maunium.telegram.sticker": {"pack": {"id": "2209456005991890946", "short_name": "PaskaAnkkaRedux"}, "id": "2209456005991890964", "emoticons": ["😵"]}}, {"body": "😣", "url": "mxc://matrix.org/SReZUfCNIemhgPCAcyZCORmq", "info": {"w": 256, "h": 188, "size": 331523, "mimetype": "image/png", "thumbnail_url": "mxc://matrix.org/SReZUfCNIemhgPCAcyZCORmq", "thumbnail_info": {"w": 256, "h": 188, "size": 331523, "mimetype": "image/png"}}, "msgtype": "m.sticker", "id": "tg-2209456005991890965", "net.maunium.telegram.sticker": {"pack": {"id": "2209456005991890946", "short_name": "PaskaAnkkaRedux"}, "id": "2209456005991890965", "emoticons": ["😣"]}}, {"body": "😴", "url": "mxc://matrix.org/rPnmmaVwiBSPqkpgNCoNXzUy", "info": {"w": 230, "h": 256, "size": 281001, "mimetype": "image/png", "thumbnail_url": "mxc://matrix.org/rPnmmaVwiBSPqkpgNCoNXzUy", "thumbnail_info": {"w": 230, "h": 256, "size": 281001, "mimetype": "image/png"}}, "msgtype": "m.sticker", "id": "tg-2209456005991890966", "net.maunium.telegram.sticker": {"pack": {"id": "2209456005991890946", "short_name": "PaskaAnkkaRedux"}, "id": "2209456005991890966", "emoticons": ["😴"]}}, {"body": "🤢", "url": "mxc://matrix.org/AZTyumdQgNrWqyznhLuZFuII", "info": {"w": 225, "h": 256, "size": 271068, "mimetype": "image/png", "thumbnail_url": "mxc://matrix.org/AZTyumdQgNrWqyznhLuZFuII", "thumbnail_info": {"w": 225, "h": 256, "size": 271068, "mimetype": "image/png"}}, "msgtype": "m.sticker", "id": "tg-2209456005991890967", "net.maunium.telegram.sticker": {"pack": {"id": "2209456005991890946", "short_name": "PaskaAnkkaRedux"}, "id": "2209456005991890967", "emoticons": ["🤢"]}}, {"body": "😡", "url": "mxc://matrix.org/siqFCiJTxTTfENETCYgoBzYZ", "info": {"w": 256, "h": 188, "size": 443737, "mimetype": "image/png", "thumbnail_url": "mxc://matrix.org/siqFCiJTxTTfENETCYgoBzYZ", "thumbnail_info": {"w": 256, "h": 188, "size": 443737, "mimetype": "image/png"}}, "msgtype": "m.sticker", "id": "tg-2209456005991890968", "net.maunium.telegram.sticker": {"pack": {"id": "2209456005991890946", "short_name": "PaskaAnkkaRedux"}, "id": "2209456005991890968", "emoticons": ["😡"]}}, {"body": "👌", "url": "mxc://matrix.org/WOmwYRPCLgIqreIOyCZOYDKy", "info": {"w": 256, "h": 186, "size": 400696, "mimetype": "image/png", "thumbnail_url": "mxc://matrix.org/WOmwYRPCLgIqreIOyCZOYDKy", "thumbnail_info": {"w": 256, "h": 186, "size": 400696, "mimetype": "image/png"}}, "msgtype": "m.sticker", "id": "tg-2209456005991890969", "net.maunium.telegram.sticker": {"pack": {"id": "2209456005991890946", "short_name": "PaskaAnkkaRedux"}, "id": "2209456005991890969", "emoticons": ["👌"]}}, {"body": "🐷", "url": "mxc://matrix.org/eHjpyJjVRRUHjYqSUCUtQvFH", "info": {"w": 256, "h": 223, "size": 334512, "mimetype": "image/png", "thumbnail_url": "mxc://matrix.org/eHjpyJjVRRUHjYqSUCUtQvFH", "thumbnail_info": {"w": 256, "h": 223, "size": 334512, "mimetype": "image/png"}}, "msgtype": "m.sticker", "id": "tg-2209456005991890970", "net.maunium.telegram.sticker": {"pack": {"id": "2209456005991890946", "short_name": "PaskaAnkkaRedux"}, "id": "2209456005991890970", "emoticons": ["🐷"]}}, {"body": "😩", "url": "mxc://matrix.org/KddaBnOdUKbIghuJwiyDyhsn", "info": {"w": 239, "h": 256, "size": 273562, "mimetype": "image/png", "thumbnail_url": "mxc://matrix.org/KddaBnOdUKbIghuJwiyDyhsn", "thumbnail_info": {"w": 239, "h": 256, "size": 273562, "mimetype": "image/png"}}, "msgtype": "m.sticker", "id": "tg-2209456005991890971", "net.maunium.telegram.sticker": {"pack": {"id": "2209456005991890946", "short_name": "PaskaAnkkaRedux"}, "id": "2209456005991890971", "emoticons": ["😩"]}}, {"body": "💯", "url": "mxc://matrix.org/zOzvOAbJLZDMOMGShQubjQsC", "info": {"w": 82, "h": 256, "size": 123203, "mimetype": "image/png", "thumbnail_url": "mxc://matrix.org/zOzvOAbJLZDMOMGShQubjQsC", "thumbnail_info": {"w": 82, "h": 256, "size": 123203, "mimetype": "image/png"}}, "msgtype": "m.sticker", "id": "tg-2209456005991890972", "net.maunium.telegram.sticker": {"pack": {"id": "2209456005991890946", "short_name": "PaskaAnkkaRedux"}, "id": "2209456005991890972", "emoticons": ["💯"]}}, {"body": "🥴", "url": "mxc://matrix.org/cEBtMAgcHORMhFawMECNVzlt", "info": {"w": 256, "h": 176, "size": 279009, "mimetype": "image/png", "thumbnail_url": "mxc://matrix.org/cEBtMAgcHORMhFawMECNVzlt", "thumbnail_info": {"w": 256, "h": 176, "size": 279009, "mimetype": "image/png"}}, "msgtype": "m.sticker", "id": "tg-2209456005991890973", "net.maunium.telegram.sticker": {"pack": {"id": "2209456005991890946", "short_name": "PaskaAnkkaRedux"}, "id": "2209456005991890973", "emoticons": ["🥴"]}}, {"body": "🥃", "url": "mxc://matrix.org/UXlCJkWModdQMzrLdsjayGlj", "info": {"w": 256, "h": 197, "size": 379838, "mimetype": "image/png", "thumbnail_url": "mxc://matrix.org/UXlCJkWModdQMzrLdsjayGlj", "thumbnail_info": {"w": 256, "h": 197, "size": 379838, "mimetype": "image/png"}}, "msgtype": "m.sticker", "id": "tg-2209456005991890974", "net.maunium.telegram.sticker": {"pack": {"id": "2209456005991890946", "short_name": "PaskaAnkkaRedux"}, "id": "2209456005991890974", "emoticons": ["🥃"]}}, {"body": "🥃", "url": "mxc://matrix.org/rgZVPaENlQLZIUYZXrDfhKnT", "info": {"w": 256, "h": 214, "size": 336560, "mimetype": "image/png", "thumbnail_url": "mxc://matrix.org/rgZVPaENlQLZIUYZXrDfhKnT", "thumbnail_info": {"w": 256, "h": 214, "size": 336560, "mimetype": "image/png"}}, "msgtype": "m.sticker", "id": "tg-2209456005991890975", "net.maunium.telegram.sticker": {"pack": {"id": "2209456005991890946", "short_name": "PaskaAnkkaRedux"}, "id": "2209456005991890975", "emoticons": ["🥃"]}}, {"body": "😣", "url": "mxc://matrix.org/FGJEAZDFKznxFffojWVkoQiG", "info": {"w": 236, "h": 256, "size": 236569, "mimetype": "image/png", "thumbnail_url": "mxc://matrix.org/FGJEAZDFKznxFffojWVkoQiG", "thumbnail_info": {"w": 236, "h": 256, "size": 236569, "mimetype": "image/png"}}, "msgtype": "m.sticker", "id": "tg-2209456005991890976", "net.maunium.telegram.sticker": {"pack": {"id": "2209456005991890946", "short_name": "PaskaAnkkaRedux"}, "id": "2209456005991890976", "emoticons": ["😣"]}}, {"body": "😈", "url": "mxc://matrix.org/XZDDTAOwkvMbObtUyyGjRdso", "info": {"w": 256, "h": 173, "size": 212923, "mimetype": "image/png", "thumbnail_url": "mxc://matrix.org/XZDDTAOwkvMbObtUyyGjRdso", "thumbnail_info": {"w": 256, "h": 173, "size": 212923, "mimetype": "image/png"}}, "msgtype": "m.sticker", "id": "tg-2209456005991890977", "net.maunium.telegram.sticker": {"pack": {"id": "2209456005991890946", "short_name": "PaskaAnkkaRedux"}, "id": "2209456005991890977", "emoticons": ["😈"]}}, {"body": "💯", "url": "mxc://matrix.org/wmeICvOhULKAzUlqhfkEFYRF", "info": {"w": 256, "h": 207, "size": 344872, "mimetype": "image/png", "thumbnail_url": "mxc://matrix.org/wmeICvOhULKAzUlqhfkEFYRF", "thumbnail_info": {"w": 256, "h": 207, "size": 344872, "mimetype": "image/png"}}, "msgtype": "m.sticker", "id": "tg-2209456005991890978", "net.maunium.telegram.sticker": {"pack": {"id": "2209456005991890946", "short_name": "PaskaAnkkaRedux"}, "id": "2209456005991890978", "emoticons": ["💯"]}}, {"body": "🍵", "url": "mxc://matrix.org/uxbcFVdTjIPisDQiiwrVXXmB", "info": {"w": 256, "h": 189, "size": 219076, "mimetype": "image/png", "thumbnail_url": "mxc://matrix.org/uxbcFVdTjIPisDQiiwrVXXmB", "thumbnail_info": {"w": 256, "h": 189, "size": 219076, "mimetype": "image/png"}}, "msgtype": "m.sticker", "id": "tg-2209456005991890979", "net.maunium.telegram.sticker": {"pack": {"id": "2209456005991890946", "short_name": "PaskaAnkkaRedux"}, "id": "2209456005991890979", "emoticons": ["🍵"]}}, {"body": "🤬", "url": "mxc://matrix.org/bryZWLOnSfVMacHhwgWxUYOa", "info": {"w": 256, "h": 170, "size": 263093, "mimetype": "image/png", "thumbnail_url": "mxc://matrix.org/bryZWLOnSfVMacHhwgWxUYOa", "thumbnail_info": {"w": 256, "h": 170, "size": 263093, "mimetype": "image/png"}}, "msgtype": "m.sticker", "id": "tg-2209456005991890980", "net.maunium.telegram.sticker": {"pack": {"id": "2209456005991890946", "short_name": "PaskaAnkkaRedux"}, "id": "2209456005991890980", "emoticons": ["🤬"]}}, {"body": "😐", "url": "mxc://matrix.org/WChIahHRSXohAHOoUrRzrXDh", "info": {"w": 197, "h": 256, "size": 179605, "mimetype": "image/png", "thumbnail_url": "mxc://matrix.org/WChIahHRSXohAHOoUrRzrXDh", "thumbnail_info": {"w": 197, "h": 256, "size": 179605, "mimetype": "image/png"}}, "msgtype": "m.sticker", "id": "tg-2209456005991890981", "net.maunium.telegram.sticker": {"pack": {"id": "2209456005991890946", "short_name": "PaskaAnkkaRedux"}, "id": "2209456005991890981", "emoticons": ["😐"]}}, {"body": "🍑", "url": "mxc://matrix.org/cJgnaICatvotUtXJzjISqqGb", "info": {"w": 256, "h": 185, "size": 276827, "mimetype": "image/png", "thumbnail_url": "mxc://matrix.org/cJgnaICatvotUtXJzjISqqGb", "thumbnail_info": {"w": 256, "h": 185, "size": 276827, "mimetype": "image/png"}}, "msgtype": "m.sticker", "id": "tg-2209456005991890982", "net.maunium.telegram.sticker": {"pack": {"id": "2209456005991890946", "short_name": "PaskaAnkkaRedux"}, "id": "2209456005991890982", "emoticons": ["🍑"]}}, {"body": "🍺", "url": "mxc://matrix.org/uzHfHoNHKxsTVKmCgSKvWTng", "info": {"w": 256, "h": 128, "size": 232202, "mimetype": "image/png", "thumbnail_url": "mxc://matrix.org/uzHfHoNHKxsTVKmCgSKvWTng", "thumbnail_info": {"w": 256, "h": 128, "size": 232202, "mimetype": "image/png"}}, "msgtype": "m.sticker", "id": "tg-2209456005991890983", "net.maunium.telegram.sticker": {"pack": {"id": "2209456005991890946", "short_name": "PaskaAnkkaRedux"}, "id": "2209456005991890983", "emoticons": ["🍺"]}}, {"body": "😕", "url": "mxc://matrix.org/ZHAzvJflyxcqCuEtEYJxhmLq", "info": {"w": 256, "h": 174, "size": 209643, "mimetype": "image/png", "thumbnail_url": "mxc://matrix.org/ZHAzvJflyxcqCuEtEYJxhmLq", "thumbnail_info": {"w": 256, "h": 174, "size": 209643, "mimetype": "image/png"}}, "msgtype": "m.sticker", "id": "tg-2209456005991890984", "net.maunium.telegram.sticker": {"pack": {"id": "2209456005991890946", "short_name": "PaskaAnkkaRedux"}, "id": "2209456005991890984", "emoticons": ["😕"]}}, {"body": "😎", "url": "mxc://matrix.org/diXdIlOULRWcVEIAroYbHGit", "info": {"w": 256, "h": 183, "size": 319232, "mimetype": "image/png", "thumbnail_url": "mxc://matrix.org/diXdIlOULRWcVEIAroYbHGit", "thumbnail_info": {"w": 256, "h": 183, "size": 319232, "mimetype": "image/png"}}, "msgtype": "m.sticker", "id": "tg-2209456005991890985", "net.maunium.telegram.sticker": {"pack": {"id": "2209456005991890946", "short_name": "PaskaAnkkaRedux"}, "id": "2209456005991890985", "emoticons": ["😎"]}}, {"body": "😥", "url": "mxc://matrix.org/DkDkXqkdGwWphhcFNTenMRcp", "info": {"w": 256, "h": 185, "size": 314191, "mimetype": "image/png", "thumbnail_url": "mxc://matrix.org/DkDkXqkdGwWphhcFNTenMRcp", "thumbnail_info": {"w": 256, "h": 185, "size": 314191, "mimetype": "image/png"}}, "msgtype": "m.sticker", "id": "tg-2209456005991890986", "net.maunium.telegram.sticker": {"pack": {"id": "2209456005991890946", "short_name": "PaskaAnkkaRedux"}, "id": "2209456005991890986", "emoticons": ["😥"]}}, {"body": "😯", "url": "mxc://matrix.org/UmEajugVodMKoCDfUkkNrKhb", "info": {"w": 256, "h": 182, "size": 289792, "mimetype": "image/png", "thumbnail_url": "mxc://matrix.org/UmEajugVodMKoCDfUkkNrKhb", "thumbnail_info": {"w": 256, "h": 182, "size": 289792, "mimetype": "image/png"}}, "msgtype": "m.sticker", "id": "tg-2209456005991890987", "net.maunium.telegram.sticker": {"pack": {"id": "2209456005991890946", "short_name": "PaskaAnkkaRedux"}, "id": "2209456005991890987", "emoticons": ["😯"]}}, {"body": "😧", "url": "mxc://matrix.org/OsxlxEkLoyNFcQVHSUABxKRA", "info": {"w": 256, "h": 191, "size": 323273, "mimetype": "image/png", "thumbnail_url": "mxc://matrix.org/OsxlxEkLoyNFcQVHSUABxKRA", "thumbnail_info": {"w": 256, "h": 191, "size": 323273, "mimetype": "image/png"}}, "msgtype": "m.sticker", "id": "tg-2209456005991890988", "net.maunium.telegram.sticker": {"pack": {"id": "2209456005991890946", "short_name": "PaskaAnkkaRedux"}, "id": "2209456005991890988", "emoticons": ["😧"]}}, {"body": "🏺", "url": "mxc://matrix.org/glbowuLKLlCXTIHIaypQkUcY", "info": {"w": 256, "h": 202, "size": 328322, "mimetype": "image/png", "thumbnail_url": "mxc://matrix.org/glbowuLKLlCXTIHIaypQkUcY", "thumbnail_info": {"w": 256, "h": 202, "size": 328322, "mimetype": "image/png"}}, "msgtype": "m.sticker", "id": "tg-2209456005991890989", "net.maunium.telegram.sticker": {"pack": {"id": "2209456005991890946", "short_name": "PaskaAnkkaRedux"}, "id": "2209456005991890989", "emoticons": ["🏺"]}}, {"body": "🐵", "url": "mxc://matrix.org/eylyXAieWeqDstFyKxQuhIwH", "info": {"w": 256, "h": 210, "size": 241068, "mimetype": "image/png", "thumbnail_url": "mxc://matrix.org/eylyXAieWeqDstFyKxQuhIwH", "thumbnail_info": {"w": 256, "h": 210, "size": 241068, "mimetype": "image/png"}}, "msgtype": "m.sticker", "id": "tg-2209456005991890990", "net.maunium.telegram.sticker": {"pack": {"id": "2209456005991890946", "short_name": "PaskaAnkkaRedux"}, "id": "2209456005991890990", "emoticons": ["🐵"]}}, {"body": "🤪", "url": "mxc://matrix.org/MEzGJGOMrOMRvpnPZTRkEGCf", "info": {"w": 256, "h": 162, "size": 330939, "mimetype": "image/png", "thumbnail_url": "mxc://matrix.org/MEzGJGOMrOMRvpnPZTRkEGCf", "thumbnail_info": {"w": 256, "h": 162, "size": 330939, "mimetype": "image/png"}}, "msgtype": "m.sticker", "id": "tg-2209456005991890991", "net.maunium.telegram.sticker": {"pack": {"id": "2209456005991890946", "short_name": "PaskaAnkkaRedux"}, "id": "2209456005991890991", "emoticons": ["🤪"]}}, {"body": "🥴", "url": "mxc://matrix.org/MipcyoPudgsBJrnMxrKMQPlD", "info": {"w": 256, "h": 196, "size": 395539, "mimetype": "image/png", "thumbnail_url": "mxc://matrix.org/MipcyoPudgsBJrnMxrKMQPlD", "thumbnail_info": {"w": 256, "h": 196, "size": 395539, "mimetype": "image/png"}}, "msgtype": "m.sticker", "id": "tg-2209456005991890992", "net.maunium.telegram.sticker": {"pack": {"id": "2209456005991890946", "short_name": "PaskaAnkkaRedux"}, "id": "2209456005991890992", "emoticons": ["🥴"]}}, {"body": "🍺", "url": "mxc://matrix.org/mqkgYdrVhwUaQeAzdothGhSa", "info": {"w": 256, "h": 196, "size": 358035, "mimetype": "image/png", "thumbnail_url": "mxc://matrix.org/mqkgYdrVhwUaQeAzdothGhSa", "thumbnail_info": {"w": 256, "h": 196, "size": 358035, "mimetype": "image/png"}}, "msgtype": "m.sticker", "id": "tg-2209456005991890993", "net.maunium.telegram.sticker": {"pack": {"id": "2209456005991890946", "short_name": "PaskaAnkkaRedux"}, "id": "2209456005991890993", "emoticons": ["🍺"]}}, {"body": "😝", "url": "mxc://matrix.org/SUGZtvdKwnkjVNvrYIjRCxHk", "info": {"w": 256, "h": 191, "size": 269883, "mimetype": "image/png", "thumbnail_url": "mxc://matrix.org/SUGZtvdKwnkjVNvrYIjRCxHk", "thumbnail_info": {"w": 256, "h": 191, "size": 269883, "mimetype": "image/png"}}, "msgtype": "m.sticker", "id": "tg-2209456005991890994", "net.maunium.telegram.sticker": {"pack": {"id": "2209456005991890946", "short_name": "PaskaAnkkaRedux"}, "id": "2209456005991890994", "emoticons": ["😝"]}}, {"body": "👌", "url": "mxc://matrix.org/eHpTQwlXLOznSQUMDKDrsVlf", "info": {"w": 256, "h": 196, "size": 287906, "mimetype": "image/png", "thumbnail_url": "mxc://matrix.org/eHpTQwlXLOznSQUMDKDrsVlf", "thumbnail_info": {"w": 256, "h": 196, "size": 287906, "mimetype": "image/png"}}, "msgtype": "m.sticker", "id": "tg-2209456005991890995", "net.maunium.telegram.sticker": {"pack": {"id": "2209456005991890946", "short_name": "PaskaAnkkaRedux"}, "id": "2209456005991890995", "emoticons": ["👌"]}}, {"body": "🤓", "url": "mxc://matrix.org/DNItOKgwjUKQPRdRokiYpNoX", "info": {"w": 256, "h": 244, "size": 287655, "mimetype": "image/png", "thumbnail_url": "mxc://matrix.org/DNItOKgwjUKQPRdRokiYpNoX", "thumbnail_info": {"w": 256, "h": 244, "size": 287655, "mimetype": "image/png"}}, "msgtype": "m.sticker", "id": "tg-2209456005991890996", "net.maunium.telegram.sticker": {"pack": {"id": "2209456005991890946", "short_name": "PaskaAnkkaRedux"}, "id": "2209456005991890996", "emoticons": ["🤓"]}}, {"body": "🤯", "url": "mxc://matrix.org/QjFnSTCNEHPimpDpdPVRrUws", "info": {"w": 256, "h": 233, "size": 413735, "mimetype": "image/png", "thumbnail_url": "mxc://matrix.org/QjFnSTCNEHPimpDpdPVRrUws", "thumbnail_info": {"w": 256, "h": 233, "size": 413735, "mimetype": "image/png"}}, "msgtype": "m.sticker", "id": "tg-2209456005991890997", "net.maunium.telegram.sticker": {"pack": {"id": "2209456005991890946", "short_name": "PaskaAnkkaRedux"}, "id": "2209456005991890997", "emoticons": ["🤯"]}}, {"body": "🙁", "url": "mxc://matrix.org/iYTjmtwFnqYffGLIiVlltvPU", "info": {"w": 256, "h": 176, "size": 268848, "mimetype": "image/png", "thumbnail_url": "mxc://matrix.org/iYTjmtwFnqYffGLIiVlltvPU", "thumbnail_info": {"w": 256, "h": 176, "size": 268848, "mimetype": "image/png"}}, "msgtype": "m.sticker", "id": "tg-2209456005991890998", "net.maunium.telegram.sticker": {"pack": {"id": "2209456005991890946", "short_name": "PaskaAnkkaRedux"}, "id": "2209456005991890998", "emoticons": ["🙁"]}}, {"body": "😫", "url": "mxc://matrix.org/FbUfEzrAAZdHKdeRjcnSePCz", "info": {"w": 256, "h": 166, "size": 310053, "mimetype": "image/png", "thumbnail_url": "mxc://matrix.org/FbUfEzrAAZdHKdeRjcnSePCz", "thumbnail_info": {"w": 256, "h": 166, "size": 310053, "mimetype": "image/png"}}, "msgtype": "m.sticker", "id": "tg-2209456005991890999", "net.maunium.telegram.sticker": {"pack": {"id": "2209456005991890946", "short_name": "PaskaAnkkaRedux"}, "id": "2209456005991890999", "emoticons": ["😫"]}}, {"body": "😫", "url": "mxc://matrix.org/EsTnJGCJHwDABQGlIwKnrcjw", "info": {"w": 256, "h": 239, "size": 441231, "mimetype": "image/png", "thumbnail_url": "mxc://matrix.org/EsTnJGCJHwDABQGlIwKnrcjw", "thumbnail_info": {"w": 256, "h": 239, "size": 441231, "mimetype": "image/png"}}, "msgtype": "m.sticker", "id": "tg-2209456005991891000", "net.maunium.telegram.sticker": {"pack": {"id": "2209456005991890946", "short_name": "PaskaAnkkaRedux"}, "id": "2209456005991891000", "emoticons": ["😫"]}}, {"body": "🌰", "url": "mxc://matrix.org/OFyElQpQgVDnakVyzJneMrhd", "info": {"w": 256, "h": 256, "size": 522681, "mimetype": "image/png", "thumbnail_url": "mxc://matrix.org/OFyElQpQgVDnakVyzJneMrhd", "thumbnail_info": {"w": 256, "h": 256, "size": 522681, "mimetype": "image/png"}}, "msgtype": "m.sticker", "id": "tg-2209456005991891001", "net.maunium.telegram.sticker": {"pack": {"id": "2209456005991890946", "short_name": "PaskaAnkkaRedux"}, "id": "2209456005991891001", "emoticons": ["🌰"]}}, {"body": "🤪", "url": "mxc://matrix.org/jfNtNogYarYcNJbJiMYWvwmX", "info": {"w": 256, "h": 248, "size": 326853, "mimetype": "image/png", "thumbnail_url": "mxc://matrix.org/jfNtNogYarYcNJbJiMYWvwmX", "thumbnail_info": {"w": 256, "h": 248, "size": 326853, "mimetype": "image/png"}}, "msgtype": "m.sticker", "id": "tg-2209456005991891002", "net.maunium.telegram.sticker": {"pack": {"id": "2209456005991890946", "short_name": "PaskaAnkkaRedux"}, "id": "2209456005991891002", "emoticons": ["🤪"]}}, {"body": "😯", "url": "mxc://matrix.org/rjZvqczcKfAUsikBSGCMeWPZ", "info": {"w": 256, "h": 232, "size": 264761, "mimetype": "image/png", "thumbnail_url": "mxc://matrix.org/rjZvqczcKfAUsikBSGCMeWPZ", "thumbnail_info": {"w": 256, "h": 232, "size": 264761, "mimetype": "image/png"}}, "msgtype": "m.sticker", "id": "tg-2209456005991891003", "net.maunium.telegram.sticker": {"pack": {"id": "2209456005991890946", "short_name": "PaskaAnkkaRedux"}, "id": "2209456005991891003", "emoticons": ["😯"]}}, {"body": "🥴", "url": "mxc://matrix.org/bsqUcsTqKpQfyeLdRBeAPOYp", "info": {"w": 256, "h": 155, "size": 121397, "mimetype": "image/png", "thumbnail_url": "mxc://matrix.org/bsqUcsTqKpQfyeLdRBeAPOYp", "thumbnail_info": {"w": 256, "h": 155, "size": 121397, "mimetype": "image/png"}}, "msgtype": "m.sticker", "id": "tg-2209456005991891004", "net.maunium.telegram.sticker": {"pack": {"id": "2209456005991890946", "short_name": "PaskaAnkkaRedux"}, "id": "2209456005991891004", "emoticons": ["🥴"]}}, {"body": "🥩", "url": "mxc://matrix.org/FXsTMtFKwkgsMSHWlOxCdsez", "info": {"w": 209, "h": 256, "size": 379654, "mimetype": "image/png", "thumbnail_url": "mxc://matrix.org/FXsTMtFKwkgsMSHWlOxCdsez", "thumbnail_info": {"w": 209, "h": 256, "size": 379654, "mimetype": "image/png"}}, "msgtype": "m.sticker", "id": "tg-2209456005991891005", "net.maunium.telegram.sticker": {"pack": {"id": "2209456005991890946", "short_name": "PaskaAnkkaRedux"}, "id": "2209456005991891005", "emoticons": ["🥩"]}}, {"body": "🤯", "url": "mxc://matrix.org/CvQGVdbRLtAGnpuwTOzeReFL", "info": {"w": 256, "h": 212, "size": 320714, "mimetype": "image/png", "thumbnail_url": "mxc://matrix.org/CvQGVdbRLtAGnpuwTOzeReFL", "thumbnail_info": {"w": 256, "h": 212, "size": 320714, "mimetype": "image/png"}}, "msgtype": "m.sticker", "id": "tg-2209456005991891006", "net.maunium.telegram.sticker": {"pack": {"id": "2209456005991890946", "short_name": "PaskaAnkkaRedux"}, "id": "2209456005991891006", "emoticons": ["🤯"]}}, {"body": "🤚", "url": "mxc://matrix.org/ePydfcESFoxsUqRbZcQVWSRw", "info": {"w": 256, "h": 166, "size": 205859, "mimetype": "image/png", "thumbnail_url": "mxc://matrix.org/ePydfcESFoxsUqRbZcQVWSRw", "thumbnail_info": {"w": 256, "h": 166, "size": 205859, "mimetype": "image/png"}}, "msgtype": "m.sticker", "id": "tg-2209456005991891007", "net.maunium.telegram.sticker": {"pack": {"id": "2209456005991890946", "short_name": "PaskaAnkkaRedux"}, "id": "2209456005991891007", "emoticons": ["🤚"]}}, {"body": "👊", "url": "mxc://matrix.org/GxHfxhZJTiMRRAzttpQSCofy", "info": {"w": 256, "h": 191, "size": 346079, "mimetype": "image/png", "thumbnail_url": "mxc://matrix.org/GxHfxhZJTiMRRAzttpQSCofy", "thumbnail_info": {"w": 256, "h": 191, "size": 346079, "mimetype": "image/png"}}, "msgtype": "m.sticker", "id": "tg-2209456005991891008", "net.maunium.telegram.sticker": {"pack": {"id": "2209456005991890946", "short_name": "PaskaAnkkaRedux"}, "id": "2209456005991891008", "emoticons": ["👊"]}}, {"body": "🤬", "url": "mxc://matrix.org/jbXlcRkfoSCQAhHfwgcdlPGA", "info": {"w": 256, "h": 252, "size": 439479, "mimetype": "image/png", "thumbnail_url": "mxc://matrix.org/jbXlcRkfoSCQAhHfwgcdlPGA", "thumbnail_info": {"w": 256, "h": 252, "size": 439479, "mimetype": "image/png"}}, "msgtype": "m.sticker", "id": "tg-2209456005991891009", "net.maunium.telegram.sticker": {"pack": {"id": "2209456005991890946", "short_name": "PaskaAnkkaRedux"}, "id": "2209456005991891009", "emoticons": ["🤬"]}}, {"body": "🍺", "url": "mxc://matrix.org/FgxsXvvlLysrTaqCcMONqxdD", "info": {"w": 256, "h": 182, "size": 178664, "mimetype": "image/png", "thumbnail_url": "mxc://matrix.org/FgxsXvvlLysrTaqCcMONqxdD", "thumbnail_info": {"w": 256, "h": 182, "size": 178664, "mimetype": "image/png"}}, "msgtype": "m.sticker", "id": "tg-2209456005991891010", "net.maunium.telegram.sticker": {"pack": {"id": "2209456005991890946", "short_name": "PaskaAnkkaRedux"}, "id": "2209456005991891010", "emoticons": ["🍺"]}}, {"body": "👌", "url": "mxc://matrix.org/sOssxDkzIMJyAjQVmHkbeUwf", "info": {"w": 256, "h": 199, "size": 337662, "mimetype": "image/png", "thumbnail_url": "mxc://matrix.org/sOssxDkzIMJyAjQVmHkbeUwf", "thumbnail_info": {"w": 256, "h": 199, "size": 337662, "mimetype": "image/png"}}, "msgtype": "m.sticker", "id": "tg-2209456005991891011", "net.maunium.telegram.sticker": {"pack": {"id": "2209456005991890946", "short_name": "PaskaAnkkaRedux"}, "id": "2209456005991891011", "emoticons": ["👌"]}}, {"body": "😠", "url": "mxc://matrix.org/VJIDyrkECLvNfrcsvZZFebeP", "info": {"w": 256, "h": 198, "size": 315313, "mimetype": "image/png", "thumbnail_url": "mxc://matrix.org/VJIDyrkECLvNfrcsvZZFebeP", "thumbnail_info": {"w": 256, "h": 198, "size": 315313, "mimetype": "image/png"}}, "msgtype": "m.sticker", "id": "tg-2209456005991891012", "net.maunium.telegram.sticker": {"pack": {"id": "2209456005991890946", "short_name": "PaskaAnkkaRedux"}, "id": "2209456005991891012", "emoticons": ["😠"]}}, {"body": "🤯", "url": "mxc://matrix.org/igRFCsmSLplCSqddBujVfmnP", "info": {"w": 237, "h": 256, "size": 415768, "mimetype": "image/png", "thumbnail_url": "mxc://matrix.org/igRFCsmSLplCSqddBujVfmnP", "thumbnail_info": {"w": 237, "h": 256, "size": 415768, "mimetype": "image/png"}}, "msgtype": "m.sticker", "id": "tg-2209456005991891013", "net.maunium.telegram.sticker": {"pack": {"id": "2209456005991890946", "short_name": "PaskaAnkkaRedux"}, "id": "2209456005991891013", "emoticons": ["🤯"]}}, {"body": "🧙‍♂️", "url": "mxc://matrix.org/GLtJHZUpkJIFNaIQIrFgYplP", "info": {"w": 256, "h": 203, "size": 395325, "mimetype": "image/png", "thumbnail_url": "mxc://matrix.org/GLtJHZUpkJIFNaIQIrFgYplP", "thumbnail_info": {"w": 256, "h": 203, "size": 395325, "mimetype": "image/png"}}, "msgtype": "m.sticker", "id": "tg-2209456005991891014", "net.maunium.telegram.sticker": {"pack": {"id": "2209456005991890946", "short_name": "PaskaAnkkaRedux"}, "id": "2209456005991891014", "emoticons": ["🧙‍♂"]}}, {"body": "🥃", "url": "mxc://matrix.org/AxqNTBJkmDGuwSWKigmeRkHo", "info": {"w": 256, "h": 256, "size": 260197, "mimetype": "image/png", "thumbnail_url": "mxc://matrix.org/AxqNTBJkmDGuwSWKigmeRkHo", "thumbnail_info": {"w": 256, "h": 256, "size": 260197, "mimetype": "image/png"}}, "msgtype": "m.sticker", "id": "tg-2209456005991891015", "net.maunium.telegram.sticker": {"pack": {"id": "2209456005991890946", "short_name": "PaskaAnkkaRedux"}, "id": "2209456005991891015", "emoticons": ["🥃"]}}, {"body": "👍", "url": "mxc://matrix.org/ggZzZoCXsObVQGAYwxAmgauX", "info": {"w": 256, "h": 180, "size": 389197, "mimetype": "image/png", "thumbnail_url": "mxc://matrix.org/ggZzZoCXsObVQGAYwxAmgauX", "thumbnail_info": {"w": 256, "h": 180, "size": 389197, "mimetype": "image/png"}}, "msgtype": "m.sticker", "id": "tg-2209456005991891016", "net.maunium.telegram.sticker": {"pack": {"id": "2209456005991890946", "short_name": "PaskaAnkkaRedux"}, "id": "2209456005991891016", "emoticons": ["👍"]}}, {"body": "🤩", "url": "mxc://matrix.org/TpNcCDulTADDqJhsSEnkbyoJ", "info": {"w": 256, "h": 179, "size": 254895, "mimetype": "image/png", "thumbnail_url": "mxc://matrix.org/TpNcCDulTADDqJhsSEnkbyoJ", "thumbnail_info": {"w": 256, "h": 179, "size": 254895, "mimetype": "image/png"}}, "msgtype": "m.sticker", "id": "tg-2209456005991891017", "net.maunium.telegram.sticker": {"pack": {"id": "2209456005991890946", "short_name": "PaskaAnkkaRedux"}, "id": "2209456005991891017", "emoticons": ["🤩"]}}, {"body": "🚫", "url": "mxc://matrix.org/nJkfQDmyPRWVQiCYboYRWReu", "info": {"w": 256, "h": 136, "size": 142598, "mimetype": "image/png", "thumbnail_url": "mxc://matrix.org/nJkfQDmyPRWVQiCYboYRWReu", "thumbnail_info": {"w": 256, "h": 136, "size": 142598, "mimetype": "image/png"}}, "msgtype": "m.sticker", "id": "tg-2209456005991891018", "net.maunium.telegram.sticker": {"pack": {"id": "2209456005991890946", "short_name": "PaskaAnkkaRedux"}, "id": "2209456005991891018", "emoticons": ["🚫"]}}, {"body": "🤴", "url": "mxc://matrix.org/udWrTIbmmhbUOBtPwwqTsrPn", "info": {"w": 253, "h": 256, "size": 409526, "mimetype": "image/png", "thumbnail_url": "mxc://matrix.org/udWrTIbmmhbUOBtPwwqTsrPn", "thumbnail_info": {"w": 253, "h": 256, "size": 409526, "mimetype": "image/png"}}, "msgtype": "m.sticker", "id": "tg-2209456005991891019", "net.maunium.telegram.sticker": {"pack": {"id": "2209456005991890946", "short_name": "PaskaAnkkaRedux"}, "id": "2209456005991891019", "emoticons": ["🤴"]}}, {"body": "😷", "url": "mxc://matrix.org/NXkZhxVRKhEPbwmiaRhLYSWK", "info": {"w": 256, "h": 155, "size": 338960, "mimetype": "image/png", "thumbnail_url": "mxc://matrix.org/NXkZhxVRKhEPbwmiaRhLYSWK", "thumbnail_info": {"w": 256, "h": 155, "size": 338960, "mimetype": "image/png"}}, "msgtype": "m.sticker", "id": "tg-2209456005991891020", "net.maunium.telegram.sticker": {"pack": {"id": "2209456005991890946", "short_name": "PaskaAnkkaRedux"}, "id": "2209456005991891020", "emoticons": ["😷"]}}, {"body": "🧛‍♂️", "url": "mxc://matrix.org/rqgboiaPtasVojEQMxXxXXSD", "info": {"w": 256, "h": 196, "size": 452393, "mimetype": "image/png", "thumbnail_url": "mxc://matrix.org/rqgboiaPtasVojEQMxXxXXSD", "thumbnail_info": {"w": 256, "h": 196, "size": 452393, "mimetype": "image/png"}}, "msgtype": "m.sticker", "id": "tg-2209456005991891021", "net.maunium.telegram.sticker": {"pack": {"id": "2209456005991890946", "short_name": "PaskaAnkkaRedux"}, "id": "2209456005991891021", "emoticons": ["🧛‍♂"]}}, {"body": "🥴", "url": "mxc://matrix.org/oWOVlclDVJYLLKVSvojBBnIb", "info": {"w": 256, "h": 238, "size": 272012, "mimetype": "image/png", "thumbnail_url": "mxc://matrix.org/oWOVlclDVJYLLKVSvojBBnIb", "thumbnail_info": {"w": 256, "h": 238, "size": 272012, "mimetype": "image/png"}}, "msgtype": "m.sticker", "id": "tg-2209456005991891022", "net.maunium.telegram.sticker": {"pack": {"id": "2209456005991890946", "short_name": "PaskaAnkkaRedux"}, "id": "2209456005991891022", "emoticons": ["🥴"]}}, {"body": "😫", "url": "mxc://matrix.org/SNCLcautWyvPLdJBuprXPtyH", "info": {"w": 256, "h": 182, "size": 244874, "mimetype": "image/png", "thumbnail_url": "mxc://matrix.org/SNCLcautWyvPLdJBuprXPtyH", "thumbnail_info": {"w": 256, "h": 182, "size": 244874, "mimetype": "image/png"}}, "msgtype": "m.sticker", "id": "tg-2209456005991891023", "net.maunium.telegram.sticker": {"pack": {"id": "2209456005991890946", "short_name": "PaskaAnkkaRedux"}, "id": "2209456005991891023", "emoticons": ["😫"]}}, {"body": "🍻", "url": "mxc://matrix.org/oyFnKwQQFRJhjXvHUEoiPbbz", "info": {"w": 256, "h": 186, "size": 381406, "mimetype": "image/png", "thumbnail_url": "mxc://matrix.org/oyFnKwQQFRJhjXvHUEoiPbbz", "thumbnail_info": {"w": 256, "h": 186, "size": 381406, "mimetype": "image/png"}}, "msgtype": "m.sticker", "id": "tg-2209456005991891024", "net.maunium.telegram.sticker": {"pack": {"id": "2209456005991890946", "short_name": "PaskaAnkkaRedux"}, "id": "2209456005991891024", "emoticons": ["🍻"]}}, {"body": "⚠️", "url": "mxc://matrix.org/EoJlPizUFOxokOkzahgjHeBP", "info": {"w": 256, "h": 194, "size": 195360, "mimetype": "image/png", "thumbnail_url": "mxc://matrix.org/EoJlPizUFOxokOkzahgjHeBP", "thumbnail_info": {"w": 256, "h": 194, "size": 195360, "mimetype": "image/png"}}, "msgtype": "m.sticker", "id": "tg-2209456005991891025", "net.maunium.telegram.sticker": {"pack": {"id": "2209456005991890946", "short_name": "PaskaAnkkaRedux"}, "id": "2209456005991891025", "emoticons": ["⚠"]}}, {"body": "☣️", "url": "mxc://matrix.org/fyJuJYoRKqdFqVxVbWjgiNhK", "info": {"w": 256, "h": 197, "size": 177415, "mimetype": "image/png", "thumbnail_url": "mxc://matrix.org/fyJuJYoRKqdFqVxVbWjgiNhK", "thumbnail_info": {"w": 256, "h": 197, "size": 177415, "mimetype": "image/png"}}, "msgtype": "m.sticker", "id": "tg-2209456005991891026", "net.maunium.telegram.sticker": {"pack": {"id": "2209456005991890946", "short_name": "PaskaAnkkaRedux"}, "id": "2209456005991891026", "emoticons": ["☣"]}}, {"body": "🍾", "url": "mxc://matrix.org/LXXyYBFJkTQXNUBqNKbaZapv", "info": {"w": 256, "h": 182, "size": 195191, "mimetype": "image/png", "thumbnail_url": "mxc://matrix.org/LXXyYBFJkTQXNUBqNKbaZapv", "thumbnail_info": {"w": 256, "h": 182, "size": 195191, "mimetype": "image/png"}}, "msgtype": "m.sticker", "id": "tg-2209456005991891027", "net.maunium.telegram.sticker": {"pack": {"id": "2209456005991890946", "short_name": "PaskaAnkkaRedux"}, "id": "2209456005991891027", "emoticons": ["🍾"]}}, {"body": "🔪", "url": "mxc://matrix.org/gDJFXLSBLYaoFfBWwClzLjLE", "info": {"w": 256, "h": 190, "size": 257112, "mimetype": "image/png", "thumbnail_url": "mxc://matrix.org/gDJFXLSBLYaoFfBWwClzLjLE", "thumbnail_info": {"w": 256, "h": 190, "size": 257112, "mimetype": "image/png"}}, "msgtype": "m.sticker", "id": "tg-2209456005991891028", "net.maunium.telegram.sticker": {"pack": {"id": "2209456005991890946", "short_name": "PaskaAnkkaRedux"}, "id": "2209456005991891028", "emoticons": ["🔪"]}}, {"body": "👷‍♂️", "url": "mxc://matrix.org/ZsAXyeeMXbAntwXgCLJWizZq", "info": {"w": 256, "h": 184, "size": 313211, "mimetype": "image/png", "thumbnail_url": "mxc://matrix.org/ZsAXyeeMXbAntwXgCLJWizZq", "thumbnail_info": {"w": 256, "h": 184, "size": 313211, "mimetype": "image/png"}}, "msgtype": "m.sticker", "id": "tg-2209456005991891029", "net.maunium.telegram.sticker": {"pack": {"id": "2209456005991890946", "short_name": "PaskaAnkkaRedux"}, "id": "2209456005991891029", "emoticons": ["👷‍♂"]}}, {"body": "😶", "url": "mxc://matrix.org/bWdsEOLmrwTnVdtUbYRoLmra", "info": {"w": 256, "h": 197, "size": 299212, "mimetype": "image/png", "thumbnail_url": "mxc://matrix.org/bWdsEOLmrwTnVdtUbYRoLmra", "thumbnail_info": {"w": 256, "h": 197, "size": 299212, "mimetype": "image/png"}}, "msgtype": "m.sticker", "id": "tg-2209456005991891030", "net.maunium.telegram.sticker": {"pack": {"id": "2209456005991890946", "short_name": "PaskaAnkkaRedux"}, "id": "2209456005991891030", "emoticons": ["😶"]}}, {"body": "🐿️", "url": "mxc://matrix.org/EbyxArUFjfdYZDeGwkxLHySh", "info": {"w": 256, "h": 166, "size": 295318, "mimetype": "image/png", "thumbnail_url": "mxc://matrix.org/EbyxArUFjfdYZDeGwkxLHySh", "thumbnail_info": {"w": 256, "h": 166, "size": 295318, "mimetype": "image/png"}}, "msgtype": "m.sticker", "id": "tg-2209456005991891031", "net.maunium.telegram.sticker": {"pack": {"id": "2209456005991890946", "short_name": "PaskaAnkkaRedux"}, "id": "2209456005991891031", "emoticons": ["🐿"]}}, {"body": "🍾", "url": "mxc://matrix.org/VOifYUbvOPTozAOXjPKsCpiG", "info": {"w": 256, "h": 202, "size": 358873, "mimetype": "image/png", "thumbnail_url": "mxc://matrix.org/VOifYUbvOPTozAOXjPKsCpiG", "thumbnail_info": {"w": 256, "h": 202, "size": 358873, "mimetype": "image/png"}}, "msgtype": "m.sticker", "id": "tg-2209456005991891032", "net.maunium.telegram.sticker": {"pack": {"id": "2209456005991890946", "short_name": "PaskaAnkkaRedux"}, "id": "2209456005991891032", "emoticons": ["🍾"]}}, {"body": "💩", "url": "mxc://matrix.org/StNZFQGXVUrernUNbhYxcvBi", "info": {"w": 256, "h": 185, "size": 261360, "mimetype": "image/png", "thumbnail_url": "mxc://matrix.org/StNZFQGXVUrernUNbhYxcvBi", "thumbnail_info": {"w": 256, "h": 185, "size": 261360, "mimetype": "image/png"}}, "msgtype": "m.sticker", "id": "tg-2209456005991891034", "net.maunium.telegram.sticker": {"pack": {"id": "2209456005991890946", "short_name": "PaskaAnkkaRedux"}, "id": "2209456005991891034", "emoticons": ["💩"]}}, {"body": "🇸🇪", "url": "mxc://matrix.org/jBLxXeeTzjFFUuaeouprOncw", "info": {"w": 185, "h": 256, "size": 283228, "mimetype": "image/png", "thumbnail_url": "mxc://matrix.org/jBLxXeeTzjFFUuaeouprOncw", "thumbnail_info": {"w": 185, "h": 256, "size": 283228, "mimetype": "image/png"}}, "msgtype": "m.sticker", "id": "tg-2209456005991891035", "net.maunium.telegram.sticker": {"pack": {"id": "2209456005991890946", "short_name": "PaskaAnkkaRedux"}, "id": "2209456005991891035", "emoticons": ["🇸🇪"]}}, {"body": "👋", "url": "mxc://matrix.org/PUjndMVBanGHMvZchlofGHVt", "info": {"w": 256, "h": 210, "size": 421539, "mimetype": "image/png", "thumbnail_url": "mxc://matrix.org/PUjndMVBanGHMvZchlofGHVt", "thumbnail_info": {"w": 256, "h": 210, "size": 421539, "mimetype": "image/png"}}, "msgtype": "m.sticker", "id": "tg-2209456005991891036", "net.maunium.telegram.sticker": {"pack": {"id": "2209456005991890946", "short_name": "PaskaAnkkaRedux"}, "id": "2209456005991891036", "emoticons": ["👋"]}}, {"body": "💦", "url": "mxc://matrix.org/nLvywzRMfzxuuqISMpUZegyL", "info": {"w": 253, "h": 256, "size": 398580, "mimetype": "image/png", "thumbnail_url": "mxc://matrix.org/nLvywzRMfzxuuqISMpUZegyL", "thumbnail_info": {"w": 253, "h": 256, "size": 398580, "mimetype": "image/png"}}, "msgtype": "m.sticker", "id": "tg-2209456005991891037", "net.maunium.telegram.sticker": {"pack": {"id": "2209456005991890946", "short_name": "PaskaAnkkaRedux"}, "id": "2209456005991891037", "emoticons": ["💦"]}}, {"body": "💩", "url": "mxc://matrix.org/NPaPoNXDDRBhGwUgujHSKEvd", "info": {"w": 256, "h": 177, "size": 384081, "mimetype": "image/png", "thumbnail_url": "mxc://matrix.org/NPaPoNXDDRBhGwUgujHSKEvd", "thumbnail_info": {"w": 256, "h": 177, "size": 384081, "mimetype": "image/png"}}, "msgtype": "m.sticker", "id": "tg-2209456005991891038", "net.maunium.telegram.sticker": {"pack": {"id": "2209456005991890946", "short_name": "PaskaAnkkaRedux"}, "id": "2209456005991891038", "emoticons": ["💩"]}}, {"body": "🍑", "url": "mxc://matrix.org/edmiHnyzkYTNSUIHjqhRtUSy", "info": {"w": 256, "h": 238, "size": 467505, "mimetype": "image/png", "thumbnail_url": "mxc://matrix.org/edmiHnyzkYTNSUIHjqhRtUSy", "thumbnail_info": {"w": 256, "h": 238, "size": 467505, "mimetype": "image/png"}}, "msgtype": "m.sticker", "id": "tg-2209456005991891039", "net.maunium.telegram.sticker": {"pack": {"id": "2209456005991890946", "short_name": "PaskaAnkkaRedux"}, "id": "2209456005991891039", "emoticons": ["🍑"]}}, {"body": "⚫", "url": "mxc://matrix.org/zBUmWUAHOojtBrkZPrmArIHs", "info": {"w": 250, "h": 256, "size": 339573, "mimetype": "image/png", "thumbnail_url": "mxc://matrix.org/zBUmWUAHOojtBrkZPrmArIHs", "thumbnail_info": {"w": 250, "h": 256, "size": 339573, "mimetype": "image/png"}}, "msgtype": "m.sticker", "id": "tg-2209456005991891040", "net.maunium.telegram.sticker": {"pack": {"id": "2209456005991890946", "short_name": "PaskaAnkkaRedux"}, "id": "2209456005991891040", "emoticons": ["⚫"]}}, {"body": "🖕", "url": "mxc://matrix.org/yfOkiiMHIUYtqZwMbrRlipnK", "info": {"w": 224, "h": 256, "size": 284696, "mimetype": "image/png", "thumbnail_url": "mxc://matrix.org/yfOkiiMHIUYtqZwMbrRlipnK", "thumbnail_info": {"w": 224, "h": 256, "size": 284696, "mimetype": "image/png"}}, "msgtype": "m.sticker", "id": "tg-2209456005991891041", "net.maunium.telegram.sticker": {"pack": {"id": "2209456005991890946", "short_name": "PaskaAnkkaRedux"}, "id": "2209456005991891041", "emoticons": ["🖕"]}}, {"body": "😷", "url": "mxc://matrix.org/TVRKzMNwbMrGazJvpxVFQAwX", "info": {"w": 256, "h": 195, "size": 361527, "mimetype": "image/png", "thumbnail_url": "mxc://matrix.org/TVRKzMNwbMrGazJvpxVFQAwX", "thumbnail_info": {"w": 256, "h": 195, "size": 361527, "mimetype": "image/png"}}, "msgtype": "m.sticker", "id": "tg-2209456005991891042", "net.maunium.telegram.sticker": {"pack": {"id": "2209456005991890946", "short_name": "PaskaAnkkaRedux"}, "id": "2209456005991891042", "emoticons": ["😷"]}}, {"body": "🔪", "url": "mxc://matrix.org/oTDOCwWguSrTgreRWNRGoHvn", "info": {"w": 256, "h": 175, "size": 238918, "mimetype": "image/png", "thumbnail_url": "mxc://matrix.org/oTDOCwWguSrTgreRWNRGoHvn", "thumbnail_info": {"w": 256, "h": 175, "size": 238918, "mimetype": "image/png"}}, "msgtype": "m.sticker", "id": "tg-2209456005991891043", "net.maunium.telegram.sticker": {"pack": {"id": "2209456005991890946", "short_name": "PaskaAnkkaRedux"}, "id": "2209456005991891043", "emoticons": ["🔪"]}}, {"body": "👌", "url": "mxc://matrix.org/nxTrdiDTWPOdISRaPlkqjgjy", "info": {"w": 140, "h": 256, "size": 196771, "mimetype": "image/png", "thumbnail_url": "mxc://matrix.org/nxTrdiDTWPOdISRaPlkqjgjy", "thumbnail_info": {"w": 140, "h": 256, "size": 196771, "mimetype": "image/png"}}, "msgtype": "m.sticker", "id": "tg-2209456005991891044", "net.maunium.telegram.sticker": {"pack": {"id": "2209456005991890946", "short_name": "PaskaAnkkaRedux"}, "id": "2209456005991891044", "emoticons": ["👌"]}}, {"body": "🖕", "url": "mxc://matrix.org/eEzRbnwIdMkTARaxpGBNcFtq", "info": {"w": 256, "h": 173, "size": 332482, "mimetype": "image/png", "thumbnail_url": "mxc://matrix.org/eEzRbnwIdMkTARaxpGBNcFtq", "thumbnail_info": {"w": 256, "h": 173, "size": 332482, "mimetype": "image/png"}}, "msgtype": "m.sticker", "id": "tg-2209456005991891045", "net.maunium.telegram.sticker": {"pack": {"id": "2209456005991890946", "short_name": "PaskaAnkkaRedux"}, "id": "2209456005991891045", "emoticons": ["🖕"]}}, {"body": "🈹", "url": "mxc://matrix.org/vZPVtINFEWdZRhAoKDClZanz", "info": {"w": 256, "h": 234, "size": 298490, "mimetype": "image/png", "thumbnail_url": "mxc://matrix.org/vZPVtINFEWdZRhAoKDClZanz", "thumbnail_info": {"w": 256, "h": 234, "size": 298490, "mimetype": "image/png"}}, "msgtype": "m.sticker", "id": "tg-2209456005991891046", "net.maunium.telegram.sticker": {"pack": {"id": "2209456005991890946", "short_name": "PaskaAnkkaRedux"}, "id": "2209456005991891046", "emoticons": ["🈹"]}}]}